poetry_plugin_pypi_proxy/__init__.py
poetry_plugin_pypi_proxy/plugin.py
poetry_plugin_pypi_proxy/utils.py
poetry_plugin_pypi_proxy-0.2.1.dist-info/LICENSE
poetry_plugin_pypi_proxy-0.2.1.dist-info/METADATA
poetry_plugin_pypi_proxy-0.2.1.dist-info/WHEEL
poetry_plugin_pypi_proxy-0.2.1.dist-info/entry_points.txt
poetry_plugin_pypi_proxy-0.2.1.dist-info/RECORD
