Metadata-Version: 2.1
Name: poetry-plugin-pypi-proxy
Version: 0.2.1
Summary: Aliases PIP_INDEX_URL silently within Poetry to point at a new repository.
License: MIT
Author: Chad Crawford
Author-email: chad@cacrawford.org
Requires-Python: >=3.9,<4.0
Classifier: License :: OSI Approved :: MIT License
Classifier: Programming Language :: Python :: 3
Classifier: Programming Language :: Python :: 3.9
Classifier: Programming Language :: Python :: 3.10
Classifier: Programming Language :: Python :: 3.11
Classifier: Programming Language :: Python :: 3.12
Provides-Extra: plugin
Requires-Dist: poetry (>=1.5.0,<2.0.0) ; extra == "plugin"
